adafruit_miniqr.py
adafruit_circuitpython_miniqr-2.1.7.dist-info/licenses/LICENSE
adafruit_circuitpython_miniqr-2.1.7.dist-info/METADATA
adafruit_circuitpython_miniqr-2.1.7.dist-info/WHEEL
adafruit_circuitpython_miniqr-2.1.7.dist-info/top_level.txt
adafruit_circuitpython_miniqr-2.1.7.dist-info/RECORD
