Metadata-Version: 2.4
Name: adafruit-circuitpython-miniqr
Version: 2.1.7
Summary: A non-hardware dependant miniature QR generator library. All native Python!
Author-email: Adafruit Industries <circuitpython@adafruit.com>
License: MIT
Project-URL: Homepage, https://github.com/adafruit/Adafruit_CircuitPython_miniQR
Keywords: adafruit,software,miniqr,qr,generator,python,micropython,circuitpython
Classifier: Intended Audience :: Developers
Classifier: Topic :: Software Development :: Libraries
Classifier: Topic :: Software Development :: Embedded Systems
Classifier: Topic :: System :: Hardware
Classifier: License :: OSI Approved :: MIT License
Classifier: Programming Language :: Python :: 3
License-File: LICENSE
Provides-Extra: optional
Dynamic: license-file
